entorno_de_prueba
keybin
venv
