Metadata-Version: 2.4
Name: keybin-cli
Version: 0.1
Summary: Safe CLI password generator and manager. Encrypt your data, manage multiple profiles and more. 
Author-email: jotaesee <joseslamich.dev@gmail.com>
Project-URL: Homepage, https://github.com/jotaesee/keybin
Project-URL: Bug Tracker, https://github.com/jotaesee/keybin/issues
Classifier: Programming Language :: Python :: 3
Classifier: License :: OSI Approved :: MIT License
Classifier: Operating System :: OS Independent
Requires-Python: >=3.9
Requires-Dist: cryptography>=45.0
Requires-Dist: keyring>=25.6
Requires-Dist: platformdirs>=4.4
Requires-Dist: pydantic>=2.0
Requires-Dist: pyperclip>=1.9
Requires-Dist: rich>=14.0
Requires-Dist: thefuzz>=0.22
Requires-Dist: typer[all]>=0.17
